wheel2conda/__init__.py
wheel2conda/__main__.py
wheel2conda/requirements.py
wheel2conda/wheel.py
wheel2conda-0.1.dist-info/entry_points.txt
wheel2conda-0.1.dist-info/WHEEL
wheel2conda-0.1.dist-info/METADATA
wheel2conda-0.1.dist-info/RECORD
