Metadata-Version: 1.2
Name: wheel2conda
Version: 0.1
Summary: Convert pure-Python wheels to conda packages
Home-page: https://www.github.com/takluyver/wheel2conda
License: UNKNOWN
Author: Thomas Kluyver
Author-email: thomas@kluyver.me.uk
Classifier: License :: OSI Approved :: MIT License
Requires-Dist: win_cli_launchers
